{
    "city": "Thetford",
    "items": [
        {
            "category": "Resources",
            "description": "Advanced material used for crafting. It can be created from a base material.",
            "listings": [
                {
                    "price": 57,
                    "quantity": 200
                },
                {
                    "price": 58,
                    "quantity": 70
                },
                {
                    "price": 59,
                    "quantity": 999
                },
                {
                    "price": 60,
                    "quantity": 999
                },
                {
                    "price": 60,
                    "quantity": 999
                }
            ],
            "name": "Neat Cloth",
            "tier": 3
        },
        {
            "category": "Resources",
            "description": "Base material used for crafting. It can be changed to a better material.",
            "listings": [
                {
                    "price": 23,
                    "quantity": 362
                },
                {
                    "price": 23,
                    "quantity": 138
                },
                {
                    "price": 24,
                    "quantity": 999
                },
                {
                    "price": 24,
                    "quantity": 999
                },
                {
                    "price": 24,
                    "quantity": 816
                }
            ],
            "name": "Flax",
            "tier": 3
        },
        {
            "category": "Resources",
            "description": "Wood, used for crafting. It can be changed to a better material.",
            "listings": [
                {
                    "price": 39,
                    "quantity": 63
                },
                {
                    "price": 40,
                    "quantity": 113
                },
                {
                    "price": 40,
                    "quantity": 999
                },
                {
                    "price": 40,
                    "quantity": 38
                },
                {
                    "price": 41,
                    "quantity": 10
                }
            ],
            "name": "Chestnut Logs",
            "tier": 3
        },
        {
            "category": "Resources",
            "description": "Advanced material used for crafting. It can be created from a base material.",
            "listings": [
                {
                    "price": 84,
                    "quantity": 10
                },
                {
                    "price": 84,
                    "quantity": 111
                },
                {
                    "price": 86,
                    "quantity": 15
                },
                {
                    "price": 87,
                    "quantity": 83
                },
                {
                    "price": 87,
                    "quantity": 999
                }
            ],
            "name": "Chestnut Planks",
            "tier": 3
        },
        {
            "category": "Resources",
            "description": "An unique building ingredient for the Explorer's House",
            "listings": [],
            "name": "Explorer's Anchor",
            "tier": 3
        },
        {
            "category": "Resources",
            "description": "Stone, used for crafting. It can be changed to a better material.",
            "listings": [
                {
                    "price": 56,
                    "quantity": 13
                },
                {
                    "price": 56,
                    "quantity": 88
                },
                {
                    "price": 56,
                    "quantity": 10
                },
                {
                    "price": 57,
                    "quantity": 17
                },
                {
                    "price": 57,
                    "quantity": 458
                }
            ],
            "name": "Sandstone",
            "tier": 3
        },
        {
            "category": "Resources",
            "description": "Advanced material used for crafting. It can be created from a base material.",
            "listings": [
                {
                    "price": 94,
                    "quantity": 201
                },
                {
                    "price": 94,
                    "quantity": 10
                },
                {
                    "price": 95,
                    "quantity": 43
                },
                {
                    "price": 100,
                    "quantity": 150
                },
                {
                    "price": 104,
                    "quantity": 179
                }
            ],
            "name": "Sandstone Block",
            "tier": 3
        },
        {
            "category": "Resources",
            "description": "Ore, used for crafting. It can be changed to a better material.",
            "listings": [
                {
                    "price": 25,
                    "quantity": 40
                },
                {
                    "price": 25,
                    "quantity": 419
                },
                {
                    "price": 28,
                    "quantity": 18
                },
                {
                    "price": 29,
                    "quantity": 103
                },
                {
                    "price": 30,
                    "quantity": 884
                }
            ],
            "name": "Tin Ore",
            "tier": 3
        },
        {
            "category": "Resources",
            "description": "Advanced material used for crafting. It can be created from a base material.",
            "listings": [
                {
                    "price": 68,
                    "quantity": 10
                },
                {
                    "price": 68,
                    "quantity": 109
                },
                {
                    "price": 70,
                    "quantity": 11
                },
                {
                    "price": 71,
                    "quantity": 25
                },
                {
                    "price": 72,
                    "quantity": 10
                }
            ],
            "name": "Bronze Bar",
            "tier": 3
        },
        {
            "category": "Resources",
            "description": "Hide, used for crafting. It can be changed to a better material.",
            "listings": [
                {
                    "price": 47,
                    "quantity": 77
                },
                {
                    "price": 48,
                    "quantity": 453
                },
                {
                    "price": 48,
                    "quantity": 276
                },
                {
                    "price": 49,
                    "quantity": 20
                },
                {
                    "price": 49,
                    "quantity": 33
                }
            ],
            "name": "Thin Hide",
            "tier": 3
        },
        {
            "category": "Resources",
            "description": "Advanced material used for crafting. It can be created from a base material.",
            "listings": [
                {
                    "price": 89,
                    "quantity": 10
                },
                {
                    "price": 90,
                    "quantity": 10
                },
                {
                    "price": 94,
                    "quantity": 24
                },
                {
                    "price": 96,
                    "quantity": 40
                },
                {
                    "price": 97,
                    "quantity": 28
                }
            ],
            "name": "Thick Leather",
            "tier": 3
        }
    ]
}